sqlitecarver/__init__.py
sqlitecarver/sqlitecarver.py
sqlite_carver-2.0.0.dist-info/LICENSE
sqlite_carver-2.0.0.dist-info/METADATA
sqlite_carver-2.0.0.dist-info/WHEEL
sqlite_carver-2.0.0.dist-info/entry_points.txt
sqlite_carver-2.0.0.dist-info/top_level.txt
sqlite_carver-2.0.0.dist-info/RECORD
