Metadata-Version: 2.1
Name: sqlite-carver
Version: 2.0.0
Summary: Python 3 SQLite Carver to carve for deleted records from SQLite databases
Author-email: "Mari DeGrazia / Corey Forman (digitalsleuth)" <github@digitalsleuth.ca>
Maintainer-email: "Corey Forman (digitalsleuth)" <github@digitalsleuth.ca>
License: GNU GENERAL PUBLIC LICENSE
Project-URL: Homepage, https://github.com/digitalsleuth/SQLite-Deleted-Records-Parser
Keywords: digital forensics,dfir,sqlite,deleted,carver
Classifier: Development Status :: 5 - Production/Stable
Classifier: Programming Language :: Python :: 3
Classifier: License :: OSI Approved :: GNU General Public License v3 or later (GPLv3+)
Classifier: Operating System :: OS Independent
Requires-Python: >=3.6
License-File: LICENSE
